LICENSE.txt
MANIFEST
README.md
tdigest/__init__.py
tdigest/__init__.pyc
tdigest/tdigest.py
tdigest/tdigest.pyc
tdigest/test_convergence_of_ks_statistic_over_adding.py
tdigest/__pycache__/test_convergence_of_ks_statistic_over_adding.cpython-27-PYTEST.pyc
tdigest-0.5.2.1.dist-info/DESCRIPTION.rst
tdigest-0.5.2.1.dist-info/METADATA
tdigest-0.5.2.1.dist-info/RECORD
tdigest-0.5.2.1.dist-info/WHEEL
tdigest-0.5.2.1.dist-info/metadata.json
tdigest-0.5.2.1.dist-info/top_level.txt
