Metadata-Version: 2.0
Name: tdigest
Version: 0.5.2.1
Summary: T-Digest data structure
Home-page: https://github.com/CamDavidsonPilon/tdigest
Author: Cam Davidson-pilon
Author-email: cam.davidson.pilon@gmail.com
License: MIT
Keywords: percentile,median,probabilistic data structure,quantitle,distributed,qdigest,tdigest,streaming,pyspark
Platform: UNKNOWN
Classifier: Development Status :: 4 - Beta
Classifier: License :: OSI Approved :: MIT License
Classifier: Programming Language :: Python
Classifier: Topic :: Scientific/Engineering
Classifier: Programming Language :: Python :: 3
Requires-Dist: accumulation-tree
Requires-Dist: pyudorandom
Provides-Extra: tests
Requires-Dist: numpy; extra == 'tests'
Requires-Dist: pytest; extra == 'tests'
Requires-Dist: pytest-cov; extra == 'tests'
Requires-Dist: pytest-timeout; extra == 'tests'
